pypi_Deploy_Demo/__init__.py
pypi_Deploy_Demo/component.py
pypi_Deploy_Demo/main.py
pypiDeployDemo-0.0.3.dist-info/LICENSE
pypiDeployDemo-0.0.3.dist-info/METADATA
pypiDeployDemo-0.0.3.dist-info/WHEEL
pypiDeployDemo-0.0.3.dist-info/entry_points.txt
pypiDeployDemo-0.0.3.dist-info/top_level.txt
pypiDeployDemo-0.0.3.dist-info/RECORD
