Metadata-Version: 2.1
Name: pypiDeployDemo
Version: 0.0.3
Summary: pypiDeployDemo
Home-page: https://github.com/Kushagrabainsla/build-flask-app
Author: Kushagra Bainsla
Author-email: kushagrabainsla@gmail.com
License: MIT
Platform: UNKNOWN
Requires-Dist: PyInquirer
